{
  "asOf": "2026-07-01T20:19:54.103Z",
  "stale": false,
  "partial": false,
  "estimated": false,
  "live": {
    "xagUsd": 59.32,
    "xauUsd": 4037.5,
    "usdInr": 95.25,
    "dxy": 120.89,
    "usdBroad": true,
    "real10y": 2.2,
    "breakeven10y": 2.24,
    "xagHistory": [
      {
        "t": "2025-12-02",
        "v": 52.38866154893731
      },
      {
        "t": "2025-12-03",
        "v": 52.7675727247321
      },
      {
        "t": "2025-12-04",
        "v": 51.46030061696165
      },
      {
        "t": "2025-12-05",
        "v": 52.74036976976356
      },
      {
        "t": "2025-12-08",
        "v": 52.60279261179433
      },
      {
        "t": "2025-12-09",
        "v": 54.214204783284366
      },
      {
        "t": "2025-12-10",
        "v": 54.60400401936132
      },
      {
        "t": "2025-12-11",
        "v": 57.25976355601152
      },
      {
        "t": "2025-12-12",
        "v": 55.98694080436622
      },
      {
        "t": "2025-12-15",
        "v": 58.02088795773476
      },
      {
        "t": "2025-12-16",
        "v": 58.13158157169189
      },
      {
        "t": "2025-12-17",
        "v": 60.53363299456163
      },
      {
        "t": "2025-12-18",
        "v": 59.87362232134224
      },
      {
        "t": "2025-12-19",
        "v": 60.85215386872327
      },
      {
        "t": "2025-12-22",
        "v": 62.551854311035015
      },
      {
        "t": "2025-12-23",
        "v": 64.67025334813961
      },
      {
        "t": "2025-12-24",
        "v": 66.00079058790432
      },
      {
        "t": "2025-12-26",
        "v": 70.96069469528845
      },
      {
        "t": "2025-12-29",
        "v": 66.8655844469444
      },
      {
        "t": "2025-12-30",
        "v": 74.63267860428137
      },
      {
        "t": "2025-12-31",
        "v": 70.98144974790542
      },
      {
        "t": "2026-01-01",
        "v": 71.13725100955007
      },
      {
        "t": "2026-01-02",
        "v": 72.05241046294066
      },
      {
        "t": "2026-01-05",
        "v": 74.15641933023082
      },
      {
        "t": "2026-01-06",
        "v": 77.73818794384867
      },
      {
        "t": "2026-01-07",
        "v": 76.0207765233038
      },
      {
        "t": "2026-01-08",
        "v": 74.0263543338312
      },
      {
        "t": "2026-01-09",
        "v": 76.2438241554274
      },
      {
        "t": "2026-01-12",
        "v": 80.55672408923212
      },
      {
        "t": "2026-01-13",
        "v": 82.14600765162162
      },
      {
        "t": "2026-01-14",
        "v": 86.20209840104579
      },
      {
        "t": "2026-01-15",
        "v": 87.13469209863462
      },
      {
        "t": "2026-01-16",
        "v": 86.43400152228597
      },
      {
        "t": "2026-01-19",
        "v": 92.96686188400093
      },
      {
        "t": "2026-01-20",
        "v": 98.72984816064405
      },
      {
        "t": "2026-01-21",
        "v": 100.2909048514745
      },
      {
        "t": "2026-01-22",
        "v": 103.32612374617902
      },
      {
        "t": "2026-01-23",
        "v": 105.84717080405267
      },
      {
        "t": "2026-01-27",
        "v": 113.82596649808265
      },
      {
        "t": "2026-01-28",
        "v": 122.74593464478315
      },
      {
        "t": "2026-01-29",
        "v": 131.11492532801202
      },
      {
        "t": "2026-01-30",
        "v": 102.40902715454419
      },
      {
        "t": "2026-02-01",
        "v": 93.19240012243858
      },
      {
        "t": "2026-02-02",
        "v": 72.79682501680236
      },
      {
        "t": "2026-02-03",
        "v": 83.4815261040144
      },
      {
        "t": "2026-02-04",
        "v": 83.93509318720375
      },
      {
        "t": "2026-02-05",
        "v": 75.62449338533726
      },
      {
        "t": "2026-02-06",
        "v": 77.04441571837236
      },
      {
        "t": "2026-02-09",
        "v": 80.85089236832319
      },
      {
        "t": "2026-02-10",
        "v": 78.29829763047175
      },
      {
        "t": "2026-02-11",
        "v": 80.50663522891651
      },
      {
        "t": "2026-02-12",
        "v": 73.42141373355547
      },
      {
        "t": "2026-02-13",
        "v": 75.18836054634617
      },
      {
        "t": "2026-02-16",
        "v": 73.14938417725583
      },
      {
        "t": "2026-02-17",
        "v": 69.42399059952858
      },
      {
        "t": "2026-02-18",
        "v": 74.02137312120311
      },
      {
        "t": "2026-02-19",
        "v": 73.63283853621358
      },
      {
        "t": "2026-02-20",
        "v": 77.32889830624218
      },
      {
        "t": "2026-02-23",
        "v": 81.69852871719992
      },
      {
        "t": "2026-02-24",
        "v": 81.01471891697975
      },
      {
        "t": "2026-02-25",
        "v": 82.45456610052712
      },
      {
        "t": "2026-02-26",
        "v": 80.08904357026324
      },
      {
        "t": "2026-02-27",
        "v": 83.69267417263762
      },
      {
        "t": "2026-03-02",
        "v": 84.40581778055645
      },
      {
        "t": "2026-03-03",
        "v": 80.37297269006328
      },
      {
        "t": "2026-03-04",
        "v": 80.353047839551
      },
      {
        "t": "2026-03-05",
        "v": 79.48354950191774
      },
      {
        "t": "2026-03-06",
        "v": 80.5188115264518
      },
      {
        "t": "2026-03-09",
        "v": 79.91055011775737
      },
      {
        "t": "2026-03-10",
        "v": 82.24784577646219
      },
      {
        "t": "2026-03-11",
        "v": 80.4225080823091
      },
      {
        "t": "2026-03-12",
        "v": 80.32814177641065
      },
      {
        "t": "2026-03-13",
        "v": 77.91280711986605
      },
      {
        "t": "2026-03-16",
        "v": 76.67331537758108
      },
      {
        "t": "2026-03-17",
        "v": 75.80990518871546
      },
      {
        "t": "2026-03-18",
        "v": 74.3423846016788
      },
      {
        "t": "2026-03-19",
        "v": 69.14670309656597
      },
      {
        "t": "2026-03-20",
        "v": 67.82944909047612
      },
      {
        "t": "2026-03-23",
        "v": 67.10163857870798
      },
      {
        "t": "2026-03-24",
        "v": 66.40371534270827
      },
      {
        "t": "2026-03-25",
        "v": 69.39714739814399
      },
      {
        "t": "2026-03-26",
        "v": 65.40498221078006
      },
      {
        "t": "2026-03-27",
        "v": 67.52421144998932
      },
      {
        "t": "2026-03-30",
        "v": 67.78185083647455
      },
      {
        "t": "2026-03-31",
        "v": 70.81762319924886
      },
      {
        "t": "2026-04-01",
        "v": 71.65391345269498
      },
      {
        "t": "2026-04-02",
        "v": 68.67985277970178
      },
      {
        "t": "2026-04-06",
        "v": 68.76564033051855
      },
      {
        "t": "2026-04-07",
        "v": 68.04308776541338
      },
      {
        "t": "2026-04-08",
        "v": 70.48526562334257
      },
      {
        "t": "2026-04-09",
        "v": 71.27672496313606
      },
      {
        "t": "2026-04-10",
        "v": 71.08467154292043
      },
      {
        "t": "2026-04-13",
        "v": 70.42576780584062
      },
      {
        "t": "2026-04-14",
        "v": 73.39291012796151
      },
      {
        "t": "2026-04-15",
        "v": 73.28996506698138
      },
      {
        "t": "2026-04-16",
        "v": 72.62192910675009
      },
      {
        "t": "2026-04-17",
        "v": 74.85461930026541
      },
      {
        "t": "2026-04-20",
        "v": 73.65746786531905
      },
      {
        "t": "2026-04-21",
        "v": 71.67300810110258
      },
      {
        "t": "2026-04-22",
        "v": 72.64462129761131
      },
      {
        "t": "2026-04-23",
        "v": 70.75840211578179
      },
      {
        "t": "2026-04-24",
        "v": 71.65612732497412
      },
      {
        "t": "2026-04-27",
        "v": 71.16852195549296
      },
      {
        "t": "2026-04-28",
        "v": 69.89609886305574
      },
      {
        "t": "2026-04-29",
        "v": 68.76923787297216
      },
      {
        "t": "2026-04-30",
        "v": 70.20382710985658
      },
      {
        "t": "2026-05-01",
        "v": 71.75658177964023
      },
      {
        "t": "2026-05-04",
        "v": 70.09783797449262
      },
      {
        "t": "2026-05-05",
        "v": 70.1833487912745
      },
      {
        "t": "2026-05-06",
        "v": 72.46225356861693
      },
      {
        "t": "2026-05-07",
        "v": 73.88079223147756
      },
      {
        "t": "2026-05-08",
        "v": 74.6974343684463
      },
      {
        "t": "2026-05-11",
        "v": 78.91126351775937
      },
      {
        "t": "2026-05-12",
        "v": 79.1641984256514
      },
      {
        "t": "2026-05-13",
        "v": 85.50168455873204
      },
      {
        "t": "2026-05-14",
        "v": 83.35229130971945
      },
      {
        "t": "2026-05-15",
        "v": 78.26398261014505
      },
      {
        "t": "2026-05-18",
        "v": 78.84982856201316
      },
      {
        "t": "2026-05-19",
        "v": 77.30758978555544
      },
      {
        "t": "2026-05-20",
        "v": 78.4123120528476
      },
      {
        "t": "2026-05-21",
        "v": 78.61515810042404
      },
      {
        "t": "2026-05-22",
        "v": 77.98835551139179
      },
      {
        "t": "2026-05-25",
        "v": 79.25635085927073
      },
      {
        "t": "2026-05-26",
        "v": 77.79962289959488
      },
      {
        "t": "2026-05-27",
        "v": 76.76159353471189
      },
      {
        "t": "2026-05-28",
        "v": 77.52953048153948
      },
      {
        "t": "2026-05-29",
        "v": 77.05686874994254
      },
      {
        "t": "2026-06-01",
        "v": 76.80255017187602
      },
      {
        "t": "2026-06-02",
        "v": 77.05022713310511
      },
      {
        "t": "2026-06-03",
        "v": 76.05011033100243
      },
      {
        "t": "2026-06-04",
        "v": 76.48153869140035
      },
      {
        "t": "2026-06-05",
        "v": 72.28901806277402
      },
      {
        "t": "2026-06-08",
        "v": 71.35421049290605
      },
      {
        "t": "2026-06-09",
        "v": 69.04707884400456
      },
      {
        "t": "2026-06-10",
        "v": 67.992445437028
      },
      {
        "t": "2026-06-11",
        "v": 68.97485126089752
      },
      {
        "t": "2026-06-12",
        "v": 70.83782478379604
      },
      {
        "t": "2026-06-15",
        "v": 72.29233887119274
      },
      {
        "t": "2026-06-16",
        "v": 71.91044590304064
      },
      {
        "t": "2026-06-17",
        "v": 72.37563581569547
      },
      {
        "t": "2026-06-18",
        "v": 68.64913530182866
      },
      {
        "t": "2026-06-19",
        "v": 67.2895409884002
      },
      {
        "t": "2026-06-20",
        "v": 64.960999
      },
      {
        "t": "2026-06-21",
        "v": 64.960999
      },
      {
        "t": "2026-06-22",
        "v": 67.63269119166732
      },
      {
        "t": "2026-06-23",
        "v": 65.1260343036081
      },
      {
        "t": "2026-06-24",
        "v": 61.337268631890396
      },
      {
        "t": "2026-06-25",
        "v": 62.6141194688859
      },
      {
        "t": "2026-06-26",
        "v": 62.88282821676683
      },
      {
        "t": "2026-06-29",
        "v": 62.54908697068608
      },
      {
        "t": "2026-06-30",
        "v": 64.10875999134205
      },
      {
        "t": "2026-07-01",
        "v": 59.32
      }
    ],
    "xauHistory": [
      {
        "t": "2026-01-23",
        "v": 4984.67331
      },
      {
        "t": "2026-01-24",
        "v": 4982.4814
      },
      {
        "t": "2026-01-25",
        "v": 4982.45467
      },
      {
        "t": "2026-01-26",
        "v": 5029.16284
      },
      {
        "t": "2026-01-27",
        "v": 5099.19537
      },
      {
        "t": "2026-01-28",
        "v": 5327.17903
      },
      {
        "t": "2026-01-29",
        "v": 5310.53137
      },
      {
        "t": "2026-01-30",
        "v": 4940.66781
      },
      {
        "t": "2026-01-31",
        "v": 4865.45982
      },
      {
        "t": "2026-02-01",
        "v": 4865.45954
      },
      {
        "t": "2026-02-02",
        "v": 4687.13788
      },
      {
        "t": "2026-02-03",
        "v": 4926.47711
      },
      {
        "t": "2026-02-04",
        "v": 4941.50845
      },
      {
        "t": "2026-02-05",
        "v": 4831.82164
      },
      {
        "t": "2026-02-06",
        "v": 4957.75097
      },
      {
        "t": "2026-02-07",
        "v": 4959.11017
      },
      {
        "t": "2026-02-08",
        "v": 5011.35623
      },
      {
        "t": "2026-02-09",
        "v": 5074.62168
      },
      {
        "t": "2026-02-10",
        "v": 5028.8494
      },
      {
        "t": "2026-02-11",
        "v": 5080.6557
      },
      {
        "t": "2026-02-12",
        "v": 4945.1794
      },
      {
        "t": "2026-02-13",
        "v": 5029.89519
      },
      {
        "t": "2026-02-14",
        "v": 5043.16482
      },
      {
        "t": "2026-02-15",
        "v": 5043.2085
      },
      {
        "t": "2026-02-16",
        "v": 4992.462
      },
      {
        "t": "2026-02-17",
        "v": 4881.25215
      },
      {
        "t": "2026-02-18",
        "v": 4980.67537
      },
      {
        "t": "2026-02-19",
        "v": 4987.51618
      },
      {
        "t": "2026-02-20",
        "v": 5079.40187
      },
      {
        "t": "2026-02-21",
        "v": 5098.61379
      },
      {
        "t": "2026-02-22",
        "v": 5098.59632
      },
      {
        "t": "2026-02-23",
        "v": 5215.65797
      },
      {
        "t": "2026-02-24",
        "v": 5154.62888
      },
      {
        "t": "2026-02-25",
        "v": 5205.26524
      },
      {
        "t": "2026-02-26",
        "v": 5187.84755
      },
      {
        "t": "2026-02-27",
        "v": 5251.01854
      },
      {
        "t": "2026-02-28",
        "v": 5277.88359
      },
      {
        "t": "2026-03-01",
        "v": 5277.8835
      },
      {
        "t": "2026-03-02",
        "v": 5330.94854
      },
      {
        "t": "2026-03-03",
        "v": 5113.42789
      },
      {
        "t": "2026-03-04",
        "v": 5136.55908
      },
      {
        "t": "2026-03-05",
        "v": 5065.44602
      },
      {
        "t": "2026-03-06",
        "v": 5161.43884
      },
      {
        "t": "2026-03-07",
        "v": 5171.10452
      },
      {
        "t": "2026-03-08",
        "v": 5171.09086
      },
      {
        "t": "2026-03-09",
        "v": 5142.17754
      },
      {
        "t": "2026-03-10",
        "v": 5197.99865
      },
      {
        "t": "2026-03-11",
        "v": 5183.31222
      },
      {
        "t": "2026-03-12",
        "v": 5083.42129
      },
      {
        "t": "2026-03-13",
        "v": 5020.31894
      },
      {
        "t": "2026-03-14",
        "v": 5019.79237
      },
      {
        "t": "2026-03-15",
        "v": 5019.79532
      },
      {
        "t": "2026-03-16",
        "v": 5012.64443
      },
      {
        "t": "2026-03-17",
        "v": 4998.9783
      },
      {
        "t": "2026-03-18",
        "v": 4841.92773
      },
      {
        "t": "2026-03-19",
        "v": 4637.62973
      },
      {
        "t": "2026-03-20",
        "v": 4500.6531
      },
      {
        "t": "2026-03-21",
        "v": 4497.5218
      },
      {
        "t": "2026-03-22",
        "v": 4497.51799
      },
      {
        "t": "2026-03-23",
        "v": 4400.00688
      },
      {
        "t": "2026-03-24",
        "v": 4399.4287
      },
      {
        "t": "2026-03-25",
        "v": 4531.47513
      },
      {
        "t": "2026-03-26",
        "v": 4362.63551
      },
      {
        "t": "2026-03-27",
        "v": 4514.84071
      },
      {
        "t": "2026-03-28",
        "v": 4507.6873
      },
      {
        "t": "2026-03-29",
        "v": 4507.67826
      },
      {
        "t": "2026-03-30",
        "v": 4513.40774
      },
      {
        "t": "2026-03-31",
        "v": 4683.73771
      },
      {
        "t": "2026-04-01",
        "v": 4768.03194
      },
      {
        "t": "2026-04-02",
        "v": 4675.33535
      },
      {
        "t": "2026-04-03",
        "v": 4676.48581
      },
      {
        "t": "2026-04-04",
        "v": 4676.50865
      },
      {
        "t": "2026-04-05",
        "v": 4676.50455
      },
      {
        "t": "2026-04-06",
        "v": 4649.76527
      },
      {
        "t": "2026-04-07",
        "v": 4706.39311
      },
      {
        "t": "2026-04-08",
        "v": 4719.47769
      },
      {
        "t": "2026-04-09",
        "v": 4766.56409
      },
      {
        "t": "2026-04-10",
        "v": 4749.58009
      },
      {
        "t": "2026-04-11",
        "v": 4750.52873
      },
      {
        "t": "2026-04-12",
        "v": 4750.50252
      },
      {
        "t": "2026-04-13",
        "v": 4740.74803
      },
      {
        "t": "2026-04-14",
        "v": 4841.71465
      },
      {
        "t": "2026-04-15",
        "v": 4790.98573
      },
      {
        "t": "2026-04-16",
        "v": 4789.6854
      },
      {
        "t": "2026-04-17",
        "v": 4830.60557
      },
      {
        "t": "2026-04-18",
        "v": 4834.10038
      },
      {
        "t": "2026-04-19",
        "v": 4834.1014
      },
      {
        "t": "2026-04-20",
        "v": 4820.47575
      },
      {
        "t": "2026-04-21",
        "v": 4719.56596
      },
      {
        "t": "2026-04-22",
        "v": 4739.78055
      },
      {
        "t": "2026-04-23",
        "v": 4693.67161
      },
      {
        "t": "2026-04-24",
        "v": 4709.65804
      },
      {
        "t": "2026-04-25",
        "v": 4708.59504
      },
      {
        "t": "2026-04-26",
        "v": 4707.28437
      },
      {
        "t": "2026-04-27",
        "v": 4681.67029
      },
      {
        "t": "2026-04-28",
        "v": 4596.47098
      },
      {
        "t": "2026-04-29",
        "v": 4543.91802
      },
      {
        "t": "2026-04-30",
        "v": 4621.32118
      },
      {
        "t": "2026-05-01",
        "v": 4614.83277
      },
      {
        "t": "2026-05-02",
        "v": 4613.27308
      },
      {
        "t": "2026-05-03",
        "v": 4613.28448
      },
      {
        "t": "2026-05-04",
        "v": 4523.59841
      },
      {
        "t": "2026-05-05",
        "v": 4556.92512
      },
      {
        "t": "2026-05-06",
        "v": 4690.91268
      },
      {
        "t": "2026-05-07",
        "v": 4689.4371
      },
      {
        "t": "2026-05-08",
        "v": 4716.2703
      },
      {
        "t": "2026-05-09",
        "v": 4715.4877
      },
      {
        "t": "2026-05-10",
        "v": 4715.48243
      },
      {
        "t": "2026-05-11",
        "v": 4735.46064
      },
      {
        "t": "2026-05-12",
        "v": 4715.30897
      },
      {
        "t": "2026-05-13",
        "v": 4688.61014
      },
      {
        "t": "2026-05-14",
        "v": 4651.91243
      },
      {
        "t": "2026-05-15",
        "v": 4540.14677
      },
      {
        "t": "2026-05-16",
        "v": 4537.72547
      },
      {
        "t": "2026-05-17",
        "v": 4537.71527
      },
      {
        "t": "2026-05-18",
        "v": 4566.17371
      },
      {
        "t": "2026-05-19",
        "v": 4481.85399
      },
      {
        "t": "2026-05-20",
        "v": 4544.05897
      },
      {
        "t": "2026-05-21",
        "v": 4543.10657
      },
      {
        "t": "2026-05-22",
        "v": 4508.84161
      },
      {
        "t": "2026-05-23",
        "v": 4505.65833
      },
      {
        "t": "2026-05-24",
        "v": 4505.64909
      },
      {
        "t": "2026-05-25",
        "v": 4571.23972
      },
      {
        "t": "2026-05-26",
        "v": 4507.58338
      },
      {
        "t": "2026-05-27",
        "v": 4456.29881
      },
      {
        "t": "2026-05-28",
        "v": 4496.36988
      },
      {
        "t": "2026-05-29",
        "v": 4540.15778
      },
      {
        "t": "2026-05-30",
        "v": 4542.52645
      },
      {
        "t": "2026-05-31",
        "v": 4542.5767
      },
      {
        "t": "2026-06-01",
        "v": 4484.65892
      },
      {
        "t": "2026-06-02",
        "v": 4488.67153
      },
      {
        "t": "2026-06-03",
        "v": 4434.46857
      },
      {
        "t": "2026-06-04",
        "v": 4475.96582
      },
      {
        "t": "2026-06-05",
        "v": 4328.95948
      },
      {
        "t": "2026-06-06",
        "v": 4330.15149
      },
      {
        "t": "2026-06-07",
        "v": 4330.1492
      },
      {
        "t": "2026-06-08",
        "v": 4330.19194
      },
      {
        "t": "2026-06-09",
        "v": 4260.08482
      },
      {
        "t": "2026-06-10",
        "v": 4071.58097
      },
      {
        "t": "2026-06-11",
        "v": 4211.07514
      },
      {
        "t": "2026-06-12",
        "v": 4217.96336
      },
      {
        "t": "2026-06-13",
        "v": 4215.38604
      },
      {
        "t": "2026-06-14",
        "v": 4215.36946
      },
      {
        "t": "2026-06-15",
        "v": 4309.42435
      },
      {
        "t": "2026-06-16",
        "v": 4331.36946
      },
      {
        "t": "2026-06-17",
        "v": 4258.07298
      },
      {
        "t": "2026-06-18",
        "v": 4209.12291
      },
      {
        "t": "2026-06-19",
        "v": 4156.6112
      },
      {
        "t": "2026-06-20",
        "v": 4156.51085
      },
      {
        "t": "2026-06-21",
        "v": 4156.5162
      },
      {
        "t": "2026-06-22",
        "v": 4191.78368
      },
      {
        "t": "2026-06-23",
        "v": 4110.44546
      },
      {
        "t": "2026-06-24",
        "v": 4001.11524
      },
      {
        "t": "2026-06-25",
        "v": 4026.44634
      },
      {
        "t": "2026-06-26",
        "v": 4088.92554
      },
      {
        "t": "2026-06-27",
        "v": 4080.81341
      },
      {
        "t": "2026-06-28",
        "v": 4080.80878
      },
      {
        "t": "2026-06-29",
        "v": 4016.52691
      },
      {
        "t": "2026-06-30",
        "v": 4007.70422
      },
      {
        "t": "2026-07-01",
        "v": 4037.5
      }
    ],
    "dxyHistory": [
      {
        "t": "2025-09-22",
        "v": 119.8152
      },
      {
        "t": "2025-09-23",
        "v": 119.6202
      },
      {
        "t": "2025-09-24",
        "v": 120.1707
      },
      {
        "t": "2025-09-25",
        "v": 120.5419
      },
      {
        "t": "2025-09-26",
        "v": 120.4349
      },
      {
        "t": "2025-09-29",
        "v": 120.115
      },
      {
        "t": "2025-09-30",
        "v": 120.1368
      },
      {
        "t": "2025-10-01",
        "v": 120.1502
      },
      {
        "t": "2025-10-02",
        "v": 120.4296
      },
      {
        "t": "2025-10-03",
        "v": 120.0881
      },
      {
        "t": "2025-10-06",
        "v": 120.2722
      },
      {
        "t": "2025-10-07",
        "v": 120.4884
      },
      {
        "t": "2025-10-08",
        "v": 120.7766
      },
      {
        "t": "2025-10-09",
        "v": 121.0902
      },
      {
        "t": "2025-10-10",
        "v": 121.1163
      },
      {
        "t": "2025-10-14",
        "v": 121.1822
      },
      {
        "t": "2025-10-15",
        "v": 120.8642
      },
      {
        "t": "2025-10-16",
        "v": 120.6698
      },
      {
        "t": "2025-10-17",
        "v": 120.7028
      },
      {
        "t": "2025-10-20",
        "v": 120.6209
      },
      {
        "t": "2025-10-21",
        "v": 120.8895
      },
      {
        "t": "2025-10-22",
        "v": 120.8958
      },
      {
        "t": "2025-10-23",
        "v": 120.9531
      },
      {
        "t": "2025-10-24",
        "v": 120.9345
      },
      {
        "t": "2025-10-27",
        "v": 120.7988
      },
      {
        "t": "2025-10-28",
        "v": 120.6361
      },
      {
        "t": "2025-10-29",
        "v": 120.5312
      },
      {
        "t": "2025-10-30",
        "v": 121.2832
      },
      {
        "t": "2025-10-31",
        "v": 121.3859
      },
      {
        "t": "2025-11-03",
        "v": 121.4512
      },
      {
        "t": "2025-11-04",
        "v": 121.8271
      },
      {
        "t": "2025-11-05",
        "v": 121.8482
      },
      {
        "t": "2025-11-06",
        "v": 121.6948
      },
      {
        "t": "2025-11-07",
        "v": 121.388
      },
      {
        "t": "2025-11-10",
        "v": 121.2984
      },
      {
        "t": "2025-11-12",
        "v": 121.0458
      },
      {
        "t": "2025-11-13",
        "v": 120.7725
      },
      {
        "t": "2025-11-14",
        "v": 120.9666
      },
      {
        "t": "2025-11-17",
        "v": 121.1146
      },
      {
        "t": "2025-11-18",
        "v": 121.2127
      },
      {
        "t": "2025-11-19",
        "v": 121.4978
      },
      {
        "t": "2025-11-20",
        "v": 121.6889
      },
      {
        "t": "2025-11-21",
        "v": 121.8653
      },
      {
        "t": "2025-11-24",
        "v": 121.9171
      },
      {
        "t": "2025-11-25",
        "v": 121.6335
      },
      {
        "t": "2025-11-26",
        "v": 121.2437
      },
      {
        "t": "2025-11-28",
        "v": 121.0527
      },
      {
        "t": "2025-12-01",
        "v": 120.9862
      },
      {
        "t": "2025-12-02",
        "v": 121.1467
      },
      {
        "t": "2025-12-03",
        "v": 120.7336
      },
      {
        "t": "2025-12-04",
        "v": 120.6766
      },
      {
        "t": "2025-12-05",
        "v": 120.6863
      },
      {
        "t": "2025-12-08",
        "v": 120.776
      },
      {
        "t": "2025-12-09",
        "v": 120.6832
      },
      {
        "t": "2025-12-10",
        "v": 120.6752
      },
      {
        "t": "2025-12-11",
        "v": 119.98
      },
      {
        "t": "2025-12-12",
        "v": 120.1442
      },
      {
        "t": "2025-12-15",
        "v": 119.9561
      },
      {
        "t": "2025-12-16",
        "v": 119.8902
      },
      {
        "t": "2025-12-17",
        "v": 120.155
      },
      {
        "t": "2025-12-18",
        "v": 120.0528
      },
      {
        "t": "2025-12-19",
        "v": 120.1652
      },
      {
        "t": "2025-12-22",
        "v": 119.9912
      },
      {
        "t": "2025-12-23",
        "v": 119.7057
      },
      {
        "t": "2025-12-24",
        "v": 119.4372
      },
      {
        "t": "2025-12-26",
        "v": 119.4723
      },
      {
        "t": "2025-12-29",
        "v": 119.5899
      },
      {
        "t": "2025-12-30",
        "v": 119.4939
      },
      {
        "t": "2025-12-31",
        "v": 119.7456
      },
      {
        "t": "2026-01-02",
        "v": 119.6059
      },
      {
        "t": "2026-01-05",
        "v": 119.6192
      },
      {
        "t": "2026-01-06",
        "v": 119.7807
      },
      {
        "t": "2026-01-07",
        "v": 119.8719
      },
      {
        "t": "2026-01-08",
        "v": 120.0904
      },
      {
        "t": "2026-01-09",
        "v": 120.2215
      },
      {
        "t": "2026-01-12",
        "v": 119.9958
      },
      {
        "t": "2026-01-13",
        "v": 120.1401
      },
      {
        "t": "2026-01-14",
        "v": 119.9537
      },
      {
        "t": "2026-01-15",
        "v": 119.9951
      },
      {
        "t": "2026-01-16",
        "v": 120.0838
      },
      {
        "t": "2026-01-20",
        "v": 119.4455
      },
      {
        "t": "2026-01-21",
        "v": 119.3431
      },
      {
        "t": "2026-01-22",
        "v": 119.1962
      },
      {
        "t": "2026-01-23",
        "v": 118.8976
      },
      {
        "t": "2026-01-26",
        "v": 118.0525
      },
      {
        "t": "2026-01-27",
        "v": 117.4523
      },
      {
        "t": "2026-01-28",
        "v": 117.5117
      },
      {
        "t": "2026-01-29",
        "v": 117.4396
      },
      {
        "t": "2026-01-30",
        "v": 117.8996
      },
      {
        "t": "2026-02-02",
        "v": 118.3609
      },
      {
        "t": "2026-02-03",
        "v": 117.9764
      },
      {
        "t": "2026-02-04",
        "v": 118.2602
      },
      {
        "t": "2026-02-05",
        "v": 118.5034
      },
      {
        "t": "2026-02-06",
        "v": 118.2407
      },
      {
        "t": "2026-02-09",
        "v": 117.6392
      },
      {
        "t": "2026-02-10",
        "v": 117.5216
      },
      {
        "t": "2026-02-11",
        "v": 117.4601
      },
      {
        "t": "2026-02-12",
        "v": 117.5376
      },
      {
        "t": "2026-02-13",
        "v": 117.5258
      },
      {
        "t": "2026-02-17",
        "v": 117.7375
      },
      {
        "t": "2026-02-18",
        "v": 117.8426
      },
      {
        "t": "2026-02-19",
        "v": 118.2354
      },
      {
        "t": "2026-02-20",
        "v": 117.9917
      },
      {
        "t": "2026-02-23",
        "v": 117.9395
      },
      {
        "t": "2026-02-24",
        "v": 117.9463
      },
      {
        "t": "2026-02-25",
        "v": 117.769
      },
      {
        "t": "2026-02-26",
        "v": 117.9042
      },
      {
        "t": "2026-02-27",
        "v": 117.8223
      },
      {
        "t": "2026-03-02",
        "v": 118.667
      },
      {
        "t": "2026-03-03",
        "v": 119.4341
      },
      {
        "t": "2026-03-04",
        "v": 119.0705
      },
      {
        "t": "2026-03-05",
        "v": 119.5683
      },
      {
        "t": "2026-03-06",
        "v": 119.491
      },
      {
        "t": "2026-03-09",
        "v": 119.5151
      },
      {
        "t": "2026-03-10",
        "v": 118.7255
      },
      {
        "t": "2026-03-11",
        "v": 119.2885
      },
      {
        "t": "2026-03-12",
        "v": 119.8227
      },
      {
        "t": "2026-03-13",
        "v": 120.5518
      },
      {
        "t": "2026-03-16",
        "v": 120.097
      },
      {
        "t": "2026-03-17",
        "v": 119.8328
      },
      {
        "t": "2026-03-18",
        "v": 119.9276
      },
      {
        "t": "2026-03-19",
        "v": 120.1802
      },
      {
        "t": "2026-03-20",
        "v": 120.2757
      },
      {
        "t": "2026-03-23",
        "v": 119.9371
      },
      {
        "t": "2026-03-24",
        "v": 120.1295
      },
      {
        "t": "2026-03-25",
        "v": 120.1282
      },
      {
        "t": "2026-03-26",
        "v": 120.389
      },
      {
        "t": "2026-03-27",
        "v": 120.8851
      },
      {
        "t": "2026-03-30",
        "v": 121.2851
      },
      {
        "t": "2026-03-31",
        "v": 121.035
      },
      {
        "t": "2026-04-01",
        "v": 120.1198
      },
      {
        "t": "2026-04-02",
        "v": 120.503
      },
      {
        "t": "2026-04-03",
        "v": 120.6565
      },
      {
        "t": "2026-04-06",
        "v": 120.4302
      },
      {
        "t": "2026-04-07",
        "v": 120.32
      },
      {
        "t": "2026-04-08",
        "v": 119.0596
      },
      {
        "t": "2026-04-09",
        "v": 118.8998
      },
      {
        "t": "2026-04-10",
        "v": 118.8552
      },
      {
        "t": "2026-04-13",
        "v": 118.9916
      },
      {
        "t": "2026-04-14",
        "v": 118.3581
      },
      {
        "t": "2026-04-15",
        "v": 118.3623
      },
      {
        "t": "2026-04-16",
        "v": 118.3616
      },
      {
        "t": "2026-04-17",
        "v": 118.0795
      },
      {
        "t": "2026-04-20",
        "v": 118.2374
      },
      {
        "t": "2026-04-21",
        "v": 118.4331
      },
      {
        "t": "2026-04-22",
        "v": 118.6004
      },
      {
        "t": "2026-04-23",
        "v": 118.7155
      },
      {
        "t": "2026-04-24",
        "v": 118.7294
      },
      {
        "t": "2026-04-27",
        "v": 118.5458
      },
      {
        "t": "2026-04-28",
        "v": 118.7717
      },
      {
        "t": "2026-04-29",
        "v": 119.0975
      },
      {
        "t": "2026-04-30",
        "v": 118.671
      },
      {
        "t": "2026-05-01",
        "v": 118.3926
      },
      {
        "t": "2026-05-04",
        "v": 118.8264
      },
      {
        "t": "2026-05-05",
        "v": 118.6207
      },
      {
        "t": "2026-05-06",
        "v": 118.0982
      },
      {
        "t": "2026-05-07",
        "v": 118.0116
      },
      {
        "t": "2026-05-08",
        "v": 118.0392
      },
      {
        "t": "2026-05-11",
        "v": 118.0562
      },
      {
        "t": "2026-05-12",
        "v": 118.5238
      },
      {
        "t": "2026-05-13",
        "v": 118.4737
      },
      {
        "t": "2026-05-14",
        "v": 118.6696
      },
      {
        "t": "2026-05-15",
        "v": 119.2825
      },
      {
        "t": "2026-05-18",
        "v": 119.0574
      },
      {
        "t": "2026-05-19",
        "v": 119.451
      },
      {
        "t": "2026-05-20",
        "v": 119.1624
      },
      {
        "t": "2026-05-21",
        "v": 119.369
      },
      {
        "t": "2026-05-22",
        "v": 119.2868
      },
      {
        "t": "2026-05-26",
        "v": 119.1696
      },
      {
        "t": "2026-05-27",
        "v": 119.1829
      },
      {
        "t": "2026-05-28",
        "v": 119.0318
      },
      {
        "t": "2026-05-29",
        "v": 118.8783
      },
      {
        "t": "2026-06-01",
        "v": 119.1653
      },
      {
        "t": "2026-06-02",
        "v": 119.0359
      },
      {
        "t": "2026-06-03",
        "v": 119.3848
      },
      {
        "t": "2026-06-04",
        "v": 119.3615
      },
      {
        "t": "2026-06-05",
        "v": 120.0831
      },
      {
        "t": "2026-06-08",
        "v": 120.034
      },
      {
        "t": "2026-06-09",
        "v": 119.9617
      },
      {
        "t": "2026-06-10",
        "v": 119.9134
      },
      {
        "t": "2026-06-11",
        "v": 120.1174
      },
      {
        "t": "2026-06-12",
        "v": 119.5073
      },
      {
        "t": "2026-06-15",
        "v": 119.3158
      },
      {
        "t": "2026-06-16",
        "v": 119.256
      },
      {
        "t": "2026-06-17",
        "v": 119.3871
      },
      {
        "t": "2026-06-18",
        "v": 120.3958
      },
      {
        "t": "2026-06-22",
        "v": 120.5463
      },
      {
        "t": "2026-06-23",
        "v": 121.0552
      },
      {
        "t": "2026-06-24",
        "v": 121.412
      },
      {
        "t": "2026-06-25",
        "v": 121.0559
      },
      {
        "t": "2026-06-26",
        "v": 120.8866
      }
    ],
    "real10yHistory": [
      {
        "t": "2025-09-24",
        "v": 1.78
      },
      {
        "t": "2025-09-25",
        "v": 1.8
      },
      {
        "t": "2025-09-26",
        "v": 1.82
      },
      {
        "t": "2025-09-29",
        "v": 1.8
      },
      {
        "t": "2025-09-30",
        "v": 1.8
      },
      {
        "t": "2025-10-01",
        "v": 1.77
      },
      {
        "t": "2025-10-02",
        "v": 1.76
      },
      {
        "t": "2025-10-03",
        "v": 1.8
      },
      {
        "t": "2025-10-06",
        "v": 1.84
      },
      {
        "t": "2025-10-07",
        "v": 1.79
      },
      {
        "t": "2025-10-08",
        "v": 1.78
      },
      {
        "t": "2025-10-09",
        "v": 1.8
      },
      {
        "t": "2025-10-10",
        "v": 1.75
      },
      {
        "t": "2025-10-14",
        "v": 1.73
      },
      {
        "t": "2025-10-15",
        "v": 1.76
      },
      {
        "t": "2025-10-16",
        "v": 1.71
      },
      {
        "t": "2025-10-17",
        "v": 1.75
      },
      {
        "t": "2025-10-20",
        "v": 1.74
      },
      {
        "t": "2025-10-21",
        "v": 1.7
      },
      {
        "t": "2025-10-22",
        "v": 1.68
      },
      {
        "t": "2025-10-23",
        "v": 1.71
      },
      {
        "t": "2025-10-24",
        "v": 1.73
      },
      {
        "t": "2025-10-27",
        "v": 1.73
      },
      {
        "t": "2025-10-28",
        "v": 1.71
      },
      {
        "t": "2025-10-29",
        "v": 1.78
      },
      {
        "t": "2025-10-30",
        "v": 1.82
      },
      {
        "t": "2025-10-31",
        "v": 1.81
      },
      {
        "t": "2025-11-03",
        "v": 1.82
      },
      {
        "t": "2025-11-04",
        "v": 1.81
      },
      {
        "t": "2025-11-05",
        "v": 1.87
      },
      {
        "t": "2025-11-06",
        "v": 1.83
      },
      {
        "t": "2025-11-07",
        "v": 1.83
      },
      {
        "t": "2025-11-10",
        "v": 1.84
      },
      {
        "t": "2025-11-12",
        "v": 1.81
      },
      {
        "t": "2025-11-13",
        "v": 1.83
      },
      {
        "t": "2025-11-14",
        "v": 1.86
      },
      {
        "t": "2025-11-17",
        "v": 1.85
      },
      {
        "t": "2025-11-18",
        "v": 1.85
      },
      {
        "t": "2025-11-19",
        "v": 1.86
      },
      {
        "t": "2025-11-20",
        "v": 1.86
      },
      {
        "t": "2025-11-21",
        "v": 1.82
      },
      {
        "t": "2025-11-24",
        "v": 1.81
      },
      {
        "t": "2025-11-25",
        "v": 1.79
      },
      {
        "t": "2025-11-26",
        "v": 1.77
      },
      {
        "t": "2025-11-28",
        "v": 1.79
      },
      {
        "t": "2025-12-01",
        "v": 1.85
      },
      {
        "t": "2025-12-02",
        "v": 1.85
      },
      {
        "t": "2025-12-03",
        "v": 1.82
      },
      {
        "t": "2025-12-04",
        "v": 1.85
      },
      {
        "t": "2025-12-05",
        "v": 1.88
      },
      {
        "t": "2025-12-08",
        "v": 1.91
      },
      {
        "t": "2025-12-09",
        "v": 1.92
      },
      {
        "t": "2025-12-10",
        "v": 1.88
      },
      {
        "t": "2025-12-11",
        "v": 1.89
      },
      {
        "t": "2025-12-12",
        "v": 1.93
      },
      {
        "t": "2025-12-15",
        "v": 1.93
      },
      {
        "t": "2025-12-16",
        "v": 1.92
      },
      {
        "t": "2025-12-17",
        "v": 1.92
      },
      {
        "t": "2025-12-18",
        "v": 1.88
      },
      {
        "t": "2025-12-19",
        "v": 1.92
      },
      {
        "t": "2025-12-22",
        "v": 1.94
      },
      {
        "t": "2025-12-23",
        "v": 1.94
      },
      {
        "t": "2025-12-24",
        "v": 1.91
      },
      {
        "t": "2025-12-26",
        "v": 1.91
      },
      {
        "t": "2025-12-29",
        "v": 1.9
      },
      {
        "t": "2025-12-30",
        "v": 1.9
      },
      {
        "t": "2025-12-31",
        "v": 1.93
      },
      {
        "t": "2026-01-02",
        "v": 1.94
      },
      {
        "t": "2026-01-05",
        "v": 1.91
      },
      {
        "t": "2026-01-06",
        "v": 1.91
      },
      {
        "t": "2026-01-07",
        "v": 1.88
      },
      {
        "t": "2026-01-08",
        "v": 1.92
      },
      {
        "t": "2026-01-09",
        "v": 1.9
      },
      {
        "t": "2026-01-12",
        "v": 1.9
      },
      {
        "t": "2026-01-13",
        "v": 1.88
      },
      {
        "t": "2026-01-14",
        "v": 1.86
      },
      {
        "t": "2026-01-15",
        "v": 1.88
      },
      {
        "t": "2026-01-16",
        "v": 1.91
      },
      {
        "t": "2026-01-20",
        "v": 1.97
      },
      {
        "t": "2026-01-21",
        "v": 1.92
      },
      {
        "t": "2026-01-22",
        "v": 1.95
      },
      {
        "t": "2026-01-23",
        "v": 1.92
      },
      {
        "t": "2026-01-26",
        "v": 1.9
      },
      {
        "t": "2026-01-27",
        "v": 1.9
      },
      {
        "t": "2026-01-28",
        "v": 1.9
      },
      {
        "t": "2026-01-29",
        "v": 1.89
      },
      {
        "t": "2026-01-30",
        "v": 1.9
      },
      {
        "t": "2026-02-02",
        "v": 1.94
      },
      {
        "t": "2026-02-03",
        "v": 1.92
      },
      {
        "t": "2026-02-04",
        "v": 1.94
      },
      {
        "t": "2026-02-05",
        "v": 1.89
      },
      {
        "t": "2026-02-06",
        "v": 1.88
      },
      {
        "t": "2026-02-09",
        "v": 1.87
      },
      {
        "t": "2026-02-10",
        "v": 1.84
      },
      {
        "t": "2026-02-11",
        "v": 1.86
      },
      {
        "t": "2026-02-12",
        "v": 1.8
      },
      {
        "t": "2026-02-13",
        "v": 1.77
      },
      {
        "t": "2026-02-17",
        "v": 1.79
      },
      {
        "t": "2026-02-18",
        "v": 1.8
      },
      {
        "t": "2026-02-19",
        "v": 1.79
      },
      {
        "t": "2026-02-20",
        "v": 1.8
      },
      {
        "t": "2026-02-23",
        "v": 1.77
      },
      {
        "t": "2026-02-24",
        "v": 1.78
      },
      {
        "t": "2026-02-25",
        "v": 1.77
      },
      {
        "t": "2026-02-26",
        "v": 1.74
      },
      {
        "t": "2026-02-27",
        "v": 1.72
      },
      {
        "t": "2026-03-02",
        "v": 1.76
      },
      {
        "t": "2026-03-03",
        "v": 1.77
      },
      {
        "t": "2026-03-04",
        "v": 1.8
      },
      {
        "t": "2026-03-05",
        "v": 1.82
      },
      {
        "t": "2026-03-06",
        "v": 1.8
      },
      {
        "t": "2026-03-09",
        "v": 1.78
      },
      {
        "t": "2026-03-10",
        "v": 1.82
      },
      {
        "t": "2026-03-11",
        "v": 1.85
      },
      {
        "t": "2026-03-12",
        "v": 1.89
      },
      {
        "t": "2026-03-13",
        "v": 1.92
      },
      {
        "t": "2026-03-16",
        "v": 1.87
      },
      {
        "t": "2026-03-17",
        "v": 1.83
      },
      {
        "t": "2026-03-18",
        "v": 1.86
      },
      {
        "t": "2026-03-19",
        "v": 1.88
      },
      {
        "t": "2026-03-20",
        "v": 2.01
      },
      {
        "t": "2026-03-23",
        "v": 2.01
      },
      {
        "t": "2026-03-24",
        "v": 2.06
      },
      {
        "t": "2026-03-25",
        "v": 2.02
      },
      {
        "t": "2026-03-26",
        "v": 2.08
      },
      {
        "t": "2026-03-27",
        "v": 2.13
      },
      {
        "t": "2026-03-30",
        "v": 2.04
      },
      {
        "t": "2026-03-31",
        "v": 2
      },
      {
        "t": "2026-04-01",
        "v": 2.02
      },
      {
        "t": "2026-04-02",
        "v": 1.97
      },
      {
        "t": "2026-04-03",
        "v": 1.99
      },
      {
        "t": "2026-04-06",
        "v": 1.98
      },
      {
        "t": "2026-04-07",
        "v": 1.96
      },
      {
        "t": "2026-04-08",
        "v": 1.96
      },
      {
        "t": "2026-04-09",
        "v": 1.95
      },
      {
        "t": "2026-04-10",
        "v": 1.95
      },
      {
        "t": "2026-04-13",
        "v": 1.92
      },
      {
        "t": "2026-04-14",
        "v": 1.89
      },
      {
        "t": "2026-04-15",
        "v": 1.9
      },
      {
        "t": "2026-04-16",
        "v": 1.93
      },
      {
        "t": "2026-04-17",
        "v": 1.9
      },
      {
        "t": "2026-04-20",
        "v": 1.91
      },
      {
        "t": "2026-04-21",
        "v": 1.92
      },
      {
        "t": "2026-04-22",
        "v": 1.92
      },
      {
        "t": "2026-04-23",
        "v": 1.92
      },
      {
        "t": "2026-04-24",
        "v": 1.89
      },
      {
        "t": "2026-04-27",
        "v": 1.91
      },
      {
        "t": "2026-04-28",
        "v": 1.92
      },
      {
        "t": "2026-04-29",
        "v": 1.96
      },
      {
        "t": "2026-04-30",
        "v": 1.94
      },
      {
        "t": "2026-05-01",
        "v": 1.91
      },
      {
        "t": "2026-05-04",
        "v": 1.95
      },
      {
        "t": "2026-05-05",
        "v": 1.96
      },
      {
        "t": "2026-05-06",
        "v": 1.94
      },
      {
        "t": "2026-05-07",
        "v": 1.96
      },
      {
        "t": "2026-05-08",
        "v": 1.93
      },
      {
        "t": "2026-05-11",
        "v": 1.95
      },
      {
        "t": "2026-05-12",
        "v": 1.99
      },
      {
        "t": "2026-05-13",
        "v": 1.99
      },
      {
        "t": "2026-05-14",
        "v": 2
      },
      {
        "t": "2026-05-15",
        "v": 2.1
      },
      {
        "t": "2026-05-18",
        "v": 2.13
      },
      {
        "t": "2026-05-19",
        "v": 2.18
      },
      {
        "t": "2026-05-20",
        "v": 2.13
      },
      {
        "t": "2026-05-21",
        "v": 2.18
      },
      {
        "t": "2026-05-22",
        "v": 2.16
      },
      {
        "t": "2026-05-26",
        "v": 2.1
      },
      {
        "t": "2026-05-27",
        "v": 2.09
      },
      {
        "t": "2026-05-28",
        "v": 2.06
      },
      {
        "t": "2026-05-29",
        "v": 2.07
      },
      {
        "t": "2026-06-01",
        "v": 2.07
      },
      {
        "t": "2026-06-02",
        "v": 2.07
      },
      {
        "t": "2026-06-03",
        "v": 2.11
      },
      {
        "t": "2026-06-04",
        "v": 2.11
      },
      {
        "t": "2026-06-05",
        "v": 2.19
      },
      {
        "t": "2026-06-08",
        "v": 2.21
      },
      {
        "t": "2026-06-09",
        "v": 2.2
      },
      {
        "t": "2026-06-10",
        "v": 2.21
      },
      {
        "t": "2026-06-11",
        "v": 2.16
      },
      {
        "t": "2026-06-12",
        "v": 2.17
      },
      {
        "t": "2026-06-15",
        "v": 2.15
      },
      {
        "t": "2026-06-16",
        "v": 2.14
      },
      {
        "t": "2026-06-17",
        "v": 2.23
      },
      {
        "t": "2026-06-18",
        "v": 2.21
      },
      {
        "t": "2026-06-22",
        "v": 2.28
      },
      {
        "t": "2026-06-23",
        "v": 2.29
      },
      {
        "t": "2026-06-24",
        "v": 2.23
      },
      {
        "t": "2026-06-25",
        "v": 2.19
      },
      {
        "t": "2026-06-26",
        "v": 2.18
      },
      {
        "t": "2026-06-29",
        "v": 2.16
      },
      {
        "t": "2026-06-30",
        "v": 2.2
      }
    ],
    "usdInrHistory": [
      {
        "t": "2026-01-23",
        "v": 91.69704
      },
      {
        "t": "2026-01-24",
        "v": 91.69517
      },
      {
        "t": "2026-01-25",
        "v": 91.69604
      },
      {
        "t": "2026-01-26",
        "v": 91.71677
      },
      {
        "t": "2026-01-27",
        "v": 91.56947
      },
      {
        "t": "2026-01-28",
        "v": 92.08923
      },
      {
        "t": "2026-01-29",
        "v": 91.87832
      },
      {
        "t": "2026-01-30",
        "v": 91.77194
      },
      {
        "t": "2026-01-31",
        "v": 91.68225
      },
      {
        "t": "2026-02-01",
        "v": 91.69599
      },
      {
        "t": "2026-02-02",
        "v": 90.82545
      },
      {
        "t": "2026-02-03",
        "v": 90.45099
      },
      {
        "t": "2026-02-04",
        "v": 90.42383
      },
      {
        "t": "2026-02-05",
        "v": 90.28045
      },
      {
        "t": "2026-02-06",
        "v": 90.60504
      },
      {
        "t": "2026-02-07",
        "v": 90.55406
      },
      {
        "t": "2026-02-08",
        "v": 90.54981
      },
      {
        "t": "2026-02-09",
        "v": 90.74503
      },
      {
        "t": "2026-02-10",
        "v": 90.55848
      },
      {
        "t": "2026-02-11",
        "v": 90.70521
      },
      {
        "t": "2026-02-12",
        "v": 90.58338
      },
      {
        "t": "2026-02-13",
        "v": 90.58994
      },
      {
        "t": "2026-02-14",
        "v": 90.5553
      },
      {
        "t": "2026-02-15",
        "v": 90.55514
      },
      {
        "t": "2026-02-16",
        "v": 90.7654
      },
      {
        "t": "2026-02-17",
        "v": 90.6178
      },
      {
        "t": "2026-02-18",
        "v": 90.78475
      },
      {
        "t": "2026-02-19",
        "v": 91.07087
      },
      {
        "t": "2026-02-20",
        "v": 90.83861
      },
      {
        "t": "2026-02-21",
        "v": 90.73458
      },
      {
        "t": "2026-02-22",
        "v": 90.72785
      },
      {
        "t": "2026-02-23",
        "v": 90.99388
      },
      {
        "t": "2026-02-24",
        "v": 90.91349
      },
      {
        "t": "2026-02-25",
        "v": 90.90727
      },
      {
        "t": "2026-02-26",
        "v": 90.9853
      },
      {
        "t": "2026-02-27",
        "v": 91.09407
      },
      {
        "t": "2026-02-28",
        "v": 91.07137
      },
      {
        "t": "2026-03-01",
        "v": 91.30728
      },
      {
        "t": "2026-03-02",
        "v": 91.52947
      },
      {
        "t": "2026-03-03",
        "v": 91.99421
      },
      {
        "t": "2026-03-04",
        "v": 92.15135
      },
      {
        "t": "2026-03-05",
        "v": 91.82736
      },
      {
        "t": "2026-03-06",
        "v": 91.88486
      },
      {
        "t": "2026-03-07",
        "v": 91.95205
      },
      {
        "t": "2026-03-08",
        "v": 91.94152
      },
      {
        "t": "2026-03-09",
        "v": 91.96736
      },
      {
        "t": "2026-03-10",
        "v": 91.95162
      },
      {
        "t": "2026-03-11",
        "v": 92.21349
      },
      {
        "t": "2026-03-12",
        "v": 92.39747
      },
      {
        "t": "2026-03-13",
        "v": 92.56258
      },
      {
        "t": "2026-03-14",
        "v": 92.52542
      },
      {
        "t": "2026-03-15",
        "v": 92.57942
      },
      {
        "t": "2026-03-16",
        "v": 92.28111
      },
      {
        "t": "2026-03-17",
        "v": 92.40574
      },
      {
        "t": "2026-03-18",
        "v": 93.06187
      },
      {
        "t": "2026-03-19",
        "v": 92.88824
      },
      {
        "t": "2026-03-20",
        "v": 93.70743
      },
      {
        "t": "2026-03-21",
        "v": 93.72204
      },
      {
        "t": "2026-03-22",
        "v": 93.99542
      },
      {
        "t": "2026-03-23",
        "v": 93.26955
      },
      {
        "t": "2026-03-24",
        "v": 94.13073
      },
      {
        "t": "2026-03-25",
        "v": 93.91198
      },
      {
        "t": "2026-03-26",
        "v": 94.23439
      },
      {
        "t": "2026-03-27",
        "v": 94.70536
      },
      {
        "t": "2026-03-28",
        "v": 94.84307
      },
      {
        "t": "2026-03-29",
        "v": 94.83086
      },
      {
        "t": "2026-03-30",
        "v": 94.40314
      },
      {
        "t": "2026-03-31",
        "v": 93.38125
      },
      {
        "t": "2026-04-01",
        "v": 92.73457
      },
      {
        "t": "2026-04-02",
        "v": 93.02563
      },
      {
        "t": "2026-04-03",
        "v": 92.70262
      },
      {
        "t": "2026-04-04",
        "v": 92.83919
      },
      {
        "t": "2026-04-05",
        "v": 92.98877
      },
      {
        "t": "2026-04-06",
        "v": 92.9413
      },
      {
        "t": "2026-04-07",
        "v": 92.89379
      },
      {
        "t": "2026-04-08",
        "v": 92.4096
      },
      {
        "t": "2026-04-09",
        "v": 92.46194
      },
      {
        "t": "2026-04-10",
        "v": 93.10578
      },
      {
        "t": "2026-04-11",
        "v": 93.10141
      },
      {
        "t": "2026-04-12",
        "v": 93.71739
      },
      {
        "t": "2026-04-13",
        "v": 93.88806
      },
      {
        "t": "2026-04-14",
        "v": 93.17595
      },
      {
        "t": "2026-04-15",
        "v": 93.37866
      },
      {
        "t": "2026-04-16",
        "v": 93.05836
      },
      {
        "t": "2026-04-17",
        "v": 92.60593
      },
      {
        "t": "2026-04-18",
        "v": 92.73095
      },
      {
        "t": "2026-04-19",
        "v": 92.72402
      },
      {
        "t": "2026-04-20",
        "v": 93.11444
      },
      {
        "t": "2026-04-21",
        "v": 93.59271
      },
      {
        "t": "2026-04-22",
        "v": 93.79596
      },
      {
        "t": "2026-04-23",
        "v": 94.10143
      },
      {
        "t": "2026-04-24",
        "v": 94.16253
      },
      {
        "t": "2026-04-25",
        "v": 94.11285
      },
      {
        "t": "2026-04-26",
        "v": 94.25013
      },
      {
        "t": "2026-04-27",
        "v": 94.24517
      },
      {
        "t": "2026-04-28",
        "v": 94.60173
      },
      {
        "t": "2026-04-29",
        "v": 94.89424
      },
      {
        "t": "2026-04-30",
        "v": 94.80548
      },
      {
        "t": "2026-05-01",
        "v": 94.91047
      },
      {
        "t": "2026-05-02",
        "v": 94.83716
      },
      {
        "t": "2026-05-03",
        "v": 94.93552
      },
      {
        "t": "2026-05-04",
        "v": 95.24185
      },
      {
        "t": "2026-05-05",
        "v": 95.13322
      },
      {
        "t": "2026-05-06",
        "v": 94.56104
      },
      {
        "t": "2026-05-07",
        "v": 94.43528
      },
      {
        "t": "2026-05-08",
        "v": 94.44479
      },
      {
        "t": "2026-05-09",
        "v": 94.46567
      },
      {
        "t": "2026-05-10",
        "v": 94.46166
      },
      {
        "t": "2026-05-11",
        "v": 95.35695
      },
      {
        "t": "2026-05-12",
        "v": 95.62919
      },
      {
        "t": "2026-05-13",
        "v": 95.6892
      },
      {
        "t": "2026-05-14",
        "v": 95.75256
      },
      {
        "t": "2026-05-15",
        "v": 95.97618
      },
      {
        "t": "2026-05-16",
        "v": 96.03667
      },
      {
        "t": "2026-05-17",
        "v": 96.0066
      },
      {
        "t": "2026-05-18",
        "v": 96.29251
      },
      {
        "t": "2026-05-19",
        "v": 96.73686
      },
      {
        "t": "2026-05-20",
        "v": 96.55044
      },
      {
        "t": "2026-05-21",
        "v": 96.18239
      },
      {
        "t": "2026-05-22",
        "v": 95.67526
      },
      {
        "t": "2026-05-23",
        "v": 95.7209
      },
      {
        "t": "2026-05-24",
        "v": 95.70603
      },
      {
        "t": "2026-05-25",
        "v": 95.24386
      },
      {
        "t": "2026-05-26",
        "v": 95.87333
      },
      {
        "t": "2026-05-27",
        "v": 95.80023
      },
      {
        "t": "2026-05-28",
        "v": 95.74626
      },
      {
        "t": "2026-05-29",
        "v": 94.99439
      },
      {
        "t": "2026-05-30",
        "v": 94.99577
      },
      {
        "t": "2026-05-31",
        "v": 94.92896
      },
      {
        "t": "2026-06-01",
        "v": 95.16656
      },
      {
        "t": "2026-06-02",
        "v": 95.35251
      },
      {
        "t": "2026-06-03",
        "v": 95.78211
      },
      {
        "t": "2026-06-04",
        "v": 95.68393
      },
      {
        "t": "2026-06-05",
        "v": 95.2059
      },
      {
        "t": "2026-06-06",
        "v": 94.95291
      },
      {
        "t": "2026-06-07",
        "v": 94.97164
      },
      {
        "t": "2026-06-08",
        "v": 95.67289
      },
      {
        "t": "2026-06-09",
        "v": 95.39851
      },
      {
        "t": "2026-06-10",
        "v": 95.4642
      },
      {
        "t": "2026-06-11",
        "v": 95.09582
      },
      {
        "t": "2026-06-12",
        "v": 95.08938
      },
      {
        "t": "2026-06-13",
        "v": 95.20531
      },
      {
        "t": "2026-06-14",
        "v": 95.09521
      },
      {
        "t": "2026-06-15",
        "v": 94.57471
      },
      {
        "t": "2026-06-16",
        "v": 94.47136
      },
      {
        "t": "2026-06-17",
        "v": 94.76145
      },
      {
        "t": "2026-06-18",
        "v": 94.35163
      },
      {
        "t": "2026-06-19",
        "v": 94.32491
      },
      {
        "t": "2026-06-20",
        "v": 94.41632
      },
      {
        "t": "2026-06-21",
        "v": 94.5432
      },
      {
        "t": "2026-06-22",
        "v": 94.59445
      },
      {
        "t": "2026-06-23",
        "v": 94.93191
      },
      {
        "t": "2026-06-24",
        "v": 94.49054
      },
      {
        "t": "2026-06-25",
        "v": 94.53208
      },
      {
        "t": "2026-06-26",
        "v": 94.2528
      },
      {
        "t": "2026-06-27",
        "v": 94.44043
      },
      {
        "t": "2026-06-28",
        "v": 94.39881
      },
      {
        "t": "2026-06-29",
        "v": 94.57974
      },
      {
        "t": "2026-06-30",
        "v": 94.5699
      },
      {
        "t": "2026-07-01",
        "v": 95.25
      }
    ],
    "asOf": "2026-07-01T20:19:54.103Z",
    "partial": false
  },
  "mcx": {
    "symbol": "SILVERM",
    "silverFut": 233066,
    "prevClose": 226026,
    "expiry": "2026-08-31",
    "dte": 61,
    "optionExpiry": "2026-07-28",
    "optionDte": 27,
    "oi": 93405,
    "oiChg": -4796
  },
  "options": {
    "atmStrike": 233000,
    "atmIv": 0.3768,
    "ivEstimated": false,
    "ivRank": 15.1,
    "ivPercentile": 56.8,
    "rv20": 0.5035,
    "expectedMove1sd": 23885,
    "chain": [
      {
        "strike": 227000,
        "type": "PE",
        "ltp": 6890,
        "iv": 0.39182880445197216,
        "oi": 109
      },
      {
        "strike": 228000,
        "type": "PE",
        "ltp": 7200,
        "iv": 0.3868646746873855,
        "oi": 133
      },
      {
        "strike": 229000,
        "type": "PE",
        "ltp": 7500,
        "iv": 0.3809085495434701,
        "oi": 65
      },
      {
        "strike": 230000,
        "type": "PE",
        "ltp": 7960,
        "iv": 0.38090536505728956,
        "oi": 1868
      },
      {
        "strike": 227000,
        "type": "CE",
        "ltp": 12953,
        "iv": 0.39170257030241185,
        "oi": 39
      },
      {
        "strike": 228000,
        "type": "CE",
        "ltp": 12350,
        "iv": 0.39035873575694857,
        "oi": 39
      },
      {
        "strike": 229000,
        "type": "CE",
        "ltp": 11771.5,
        "iv": 0.3893718336932361,
        "oi": 72
      },
      {
        "strike": 230000,
        "type": "CE",
        "ltp": 11200,
        "iv": 0.3880108476169407,
        "oi": 1782
      },
      {
        "strike": 231000,
        "type": "PE",
        "ltp": 8419.5,
        "iv": 0.38019373947661367,
        "oi": 125
      },
      {
        "strike": 234000,
        "type": "PE",
        "ltp": 9831.5,
        "iv": 0.37536286928504703,
        "oi": 34
      },
      {
        "strike": 235000,
        "type": "PE",
        "ltp": 10452,
        "iv": 0.3784270712770522,
        "oi": 659
      },
      {
        "strike": 232000,
        "type": "PE",
        "ltp": 8815.5,
        "iv": 0.3762423554640264,
        "oi": 26
      },
      {
        "strike": 233000,
        "type": "PE",
        "ltp": 9386,
        "iv": 0.37865783478878445,
        "oi": 12
      },
      {
        "strike": 236000,
        "type": "PE",
        "ltp": 10745.5,
        "iv": 0.36765410351008176,
        "oi": 22
      },
      {
        "strike": 237000,
        "type": "PE",
        "ltp": 10850,
        "iv": 0.3484595478773116,
        "oi": 21
      },
      {
        "strike": 238000,
        "type": "PE",
        "ltp": 11836,
        "iv": 0.3642735246783122,
        "oi": 11
      },
      {
        "strike": 231000,
        "type": "CE",
        "ltp": 10700,
        "iv": 0.3888945052865891,
        "oi": 59
      },
      {
        "strike": 232000,
        "type": "CE",
        "ltp": 10065,
        "iv": 0.3836491444222628,
        "oi": 98
      },
      {
        "strike": 235000,
        "type": "CE",
        "ltp": 8500,
        "iv": 0.3777035038731992,
        "oi": 963
      },
      {
        "strike": 236000,
        "type": "CE",
        "ltp": 8080.5,
        "iv": 0.3784929538266734,
        "oi": 112
      },
      {
        "strike": 233000,
        "type": "CE",
        "ltp": 9360,
        "iv": 0.374956139633432,
        "oi": 108
      },
      {
        "strike": 234000,
        "type": "CE",
        "ltp": 9049.5,
        "iv": 0.38147041581571095,
        "oi": 142
      },
      {
        "strike": 237000,
        "type": "CE",
        "ltp": 7671,
        "iv": 0.37902670443803077,
        "oi": 56
      },
      {
        "strike": 238000,
        "type": "CE",
        "ltp": 7382.5,
        "iv": 0.3838259578961879,
        "oi": 47
      },
      {
        "strike": 239000,
        "type": "CE",
        "ltp": 6951,
        "iv": 0.38218398281559346,
        "oi": 41
      },
      {
        "strike": 239000,
        "type": "PE",
        "ltp": 12162.5,
        "iv": 0.3525273378957062,
        "oi": 38
      }
    ]
  },
  "basis": {
    "fairValue": 214357,
    "basis": 18709
  },
  "cot": {
    "net": 11741,
    "percentile": 30,
    "asOf": "2026-06-23",
    "source": "managed money",
    "history": [
      {
        "t": "2024-12-31",
        "v": 17170
      },
      {
        "t": "2025-01-07",
        "v": 25439
      },
      {
        "t": "2025-01-14",
        "v": 29343
      },
      {
        "t": "2025-01-21",
        "v": 29221
      },
      {
        "t": "2025-01-28",
        "v": 25950
      },
      {
        "t": "2025-02-04",
        "v": 36247
      },
      {
        "t": "2025-02-11",
        "v": 34376
      },
      {
        "t": "2025-02-18",
        "v": 38306
      },
      {
        "t": "2025-02-25",
        "v": 32939
      },
      {
        "t": "2025-03-04",
        "v": 34098
      },
      {
        "t": "2025-03-11",
        "v": 41977
      },
      {
        "t": "2025-03-18",
        "v": 49488
      },
      {
        "t": "2025-03-25",
        "v": 45392
      },
      {
        "t": "2025-04-01",
        "v": 41019
      },
      {
        "t": "2025-04-08",
        "v": 22685
      },
      {
        "t": "2025-04-15",
        "v": 23552
      },
      {
        "t": "2025-04-22",
        "v": 25891
      },
      {
        "t": "2025-04-29",
        "v": 30738
      },
      {
        "t": "2025-05-06",
        "v": 29882
      },
      {
        "t": "2025-05-13",
        "v": 28333
      },
      {
        "t": "2025-05-20",
        "v": 30445
      },
      {
        "t": "2025-05-27",
        "v": 33212
      },
      {
        "t": "2025-06-03",
        "v": 44833
      },
      {
        "t": "2025-06-10",
        "v": 47933
      },
      {
        "t": "2025-06-17",
        "v": 48865
      },
      {
        "t": "2025-06-24",
        "v": 45111
      },
      {
        "t": "2025-07-01",
        "v": 44927
      },
      {
        "t": "2025-07-08",
        "v": 42756
      },
      {
        "t": "2025-07-15",
        "v": 43206
      },
      {
        "t": "2025-07-22",
        "v": 44014
      },
      {
        "t": "2025-07-29",
        "v": 43024
      },
      {
        "t": "2025-08-05",
        "v": 29823
      },
      {
        "t": "2025-08-12",
        "v": 27280
      },
      {
        "t": "2025-08-19",
        "v": 28046
      },
      {
        "t": "2025-08-26",
        "v": 32971
      },
      {
        "t": "2025-09-02",
        "v": 38770
      },
      {
        "t": "2025-09-09",
        "v": 35855
      },
      {
        "t": "2025-09-16",
        "v": 35806
      },
      {
        "t": "2025-09-23",
        "v": 37099
      },
      {
        "t": "2025-09-30",
        "v": 34921
      },
      {
        "t": "2025-10-07",
        "v": 27493
      },
      {
        "t": "2025-10-14",
        "v": 23038
      },
      {
        "t": "2025-10-21",
        "v": 17212
      },
      {
        "t": "2025-10-28",
        "v": 21899
      },
      {
        "t": "2025-11-04",
        "v": 19157
      },
      {
        "t": "2025-11-10",
        "v": 22655
      },
      {
        "t": "2025-11-18",
        "v": 20234
      },
      {
        "t": "2025-11-25",
        "v": 19061
      },
      {
        "t": "2025-12-02",
        "v": 18974
      },
      {
        "t": "2025-12-09",
        "v": 25775
      },
      {
        "t": "2025-12-16",
        "v": 21887
      },
      {
        "t": "2025-12-23",
        "v": 21608
      },
      {
        "t": "2025-12-30",
        "v": 14008
      },
      {
        "t": "2026-01-06",
        "v": 15822
      },
      {
        "t": "2026-01-13",
        "v": 13792
      },
      {
        "t": "2026-01-20",
        "v": 9946
      },
      {
        "t": "2026-01-27",
        "v": 7699
      },
      {
        "t": "2026-02-03",
        "v": 4983
      },
      {
        "t": "2026-02-10",
        "v": 4569
      },
      {
        "t": "2026-02-17",
        "v": 5968
      },
      {
        "t": "2026-02-24",
        "v": 8523
      },
      {
        "t": "2026-03-03",
        "v": 7766
      },
      {
        "t": "2026-03-10",
        "v": 10289
      },
      {
        "t": "2026-03-17",
        "v": 9647
      },
      {
        "t": "2026-03-24",
        "v": 11158
      },
      {
        "t": "2026-03-31",
        "v": 11266
      },
      {
        "t": "2026-04-07",
        "v": 10398
      },
      {
        "t": "2026-04-14",
        "v": 11270
      },
      {
        "t": "2026-04-21",
        "v": 8868
      },
      {
        "t": "2026-04-28",
        "v": 10606
      },
      {
        "t": "2026-05-05",
        "v": 10843
      },
      {
        "t": "2026-05-12",
        "v": 15761
      },
      {
        "t": "2026-05-19",
        "v": 11564
      },
      {
        "t": "2026-05-26",
        "v": 10055
      },
      {
        "t": "2026-06-02",
        "v": 10444
      },
      {
        "t": "2026-06-09",
        "v": 10403
      },
      {
        "t": "2026-06-16",
        "v": 12885
      },
      {
        "t": "2026-06-23",
        "v": 11741
      }
    ]
  },
  "news": [
    {
      "title": "Gold (XAUUSD), Silver, Platinum Forecasts – Gold Rallies As Eurozone Inflation Falls More Than Expected",
      "url": "https://news.google.com/rss/articles/CBMi4gFBVV95cUxNQllCWU9XUXFlYlN1X2NyYzc5MVpzQ3NjaFlXTWxIaWs4b1JOSkhJeGxDa2RWNmh6aGZiSnRDZ3FEM2s1NmZBaW51b1Q2eUNSVHlxU1pUMVBEUjB0QkxJRGIxWlVlS1JSNFBRaVBmNENlc1h5VFR4Z3dUaWxmemFOWkcwSHRTOEhBMm1tMFBHQjJkNk44X3NmRURiaW9nZmdmS0gtdG1sVUNKZ1NhYjNYUWJCZlNQOEhaREM4cTNXSGVtUlIwSERJS2cyQWxlZVpOdklmbXI0eklrc3JfbEN4OUNn?oc=5",
      "source": "FXEmpire",
      "publishedAt": "2026-07-01T17:57:00.000Z",
      "snippet": "<a href=\"https://news.google.com/rss/articles/CBMi4gFBVV95cUxNQllCWU9XUXFlYlN1X2NyYzc5MVpzQ3NjaFlXTWxIaWs4b1JOSkhJeGxDa2RWNmh6aGZiSnRDZ3FEM2s1NmZBaW51b1Q2eUNSVHlxU1pUMVBEUjB0QkxJRGIxWlVlS1JSNFBRaVBmNE",
      "impact": "up"
    },
    {
      "title": "Gold, silver prices set for consolidation, carry Q1 losing-streak into Q2",
      "url": "https://news.google.com/rss/articles/CBMiwwFBVV95cUxNQWEwdzFMMGltWEN5cTFGb25aY1h4bnV5VXoyZzlWOHV4eUJlb2J6eGdVQ1VMNTR0NGtPaDJiWFVWZGZXT3RkeDJhR0lwYktGOFFHYUJ2WnRYRDU5RU5lSVZzdG5YOGZBMEQ2NUxvTTNGdUNhc0lXdk9Lck5HMGFCYW90emFkMVhZWmdGSXlva2R2UGRJcTV0VDQxT1BIaHo0WldvcFVVUzd6R0R1c0dXVWtSY0hkUUF4ei1WZE9UZmZJS3PSAdABQVVfeXFMT1R6anJDVEduMjNVSllTbURkRDZLRklHUUs2dkcxVE1Jakc5MkxGOGRhYkp3Ni1NdmVvc1pTUjdlNlE4LW81dThrRV9XWl8wNlp3WGFySmRQQWEzUTNXRGdUX1N1UEVhbmR1QXZQU1RBNGd3SVF0aXd5QUlfVUlJVnJWNERxUXQ0aG1vd0VmS2FQMlNYTkRfYmVnSnhHWmNyX2wzTFFhcjhzS3JkdDBUaUJTN3ZQVjJ1NXpiLWdEc3ZvYzJjcmhzcnJUZ3NkckNheA?oc=5",
      "source": "The New Indian Express",
      "publishedAt": "2026-07-01T17:43:43.000Z",
      "snippet": "<a href=\"https://news.google.com/rss/articles/CBMiwwFBVV95cUxNQWEwdzFMMGltWEN5cTFGb25aY1h4bnV5VXoyZzlWOHV4eUJlb2J6eGdVQ1VMNTR0NGtPaDJiWFVWZGZXT3RkeDJhR0lwYktGOFFHYUJ2WnRYRDU5RU5lSVZzdG5YOGZBMEQ2NUxvTT",
      "impact": "twoway"
    },
    {
      "title": "Is Silver Set for a Relief Rally? Why Sellers Are Waiting Near $60",
      "url": "https://news.google.com/rss/articles/CBMitgFBVV95cUxQNDFqclJhVEtETHZicW55UHJDN0lhVjZ6VXdqenBDYl92LU1OV3hMZDRUd1Rad0w5VlZCQW82VXZQQm0wa1ZJb2RJQXZnbzlVZF9wTkJOdHpQRG5hYjVic0RuQXFvSDF4d3M4dXoyRWpuLThnZjlRaFBMT3dhQXZrb29EOVI5R203RXdUVEhWZmFPc3BRNy1jRGNzeE92SUxmbjZYWnQxTThTN0x5cFR1Q0lIZEJIUQ?oc=5",
      "source": "FXEmpire",
      "publishedAt": "2026-07-01T13:20:00.000Z",
      "snippet": "<a href=\"https://news.google.com/rss/articles/CBMitgFBVV95cUxQNDFqclJhVEtETHZicW55UHJDN0lhVjZ6VXdqenBDYl92LU1OV3hMZDRUd1Rad0w5VlZCQW82VXZQQm0wa1ZJb2RJQXZnbzlVZF9wTkJOdHpQRG5hYjVic0RuQXFvSDF4d3M4dXoyRW",
      "impact": "up"
    },
    {
      "title": "Silver price crash: It was being called the 'new gold'. So what went wrong?",
      "url": "https://news.google.com/rss/articles/CBMi7AFBVV95cUxNZ1Q0c3phWFA1b1pQbllTLU5USkNtaUE4Ukt4cnRsT0w3V043a1FjcVd2T25NVWNkOFBSQVhJTXhCRVVvcTlmZWJZdHU1UkxIcGpGallDQWVCb2o5dVlwdzExbFo2aVE2UTd1SGtpS1hNWjlidW9oWkUxXzdkbUYzS3J3VHRHaWlwdjRxWTgyQm4wVzc1RHNHc19hRHp5MU5NOUZzbGNzZG10Yktab0R1bVZWek5lRndyMVNwMmgxdWZBTWtuSHk4UnB3c01SamNXWFBWWnlxOEhSU0FEdVRjcXRIZzBfelJiS0lVaQ?oc=5",
      "source": "The Times of India",
      "publishedAt": "2026-07-01T13:08:00.000Z",
      "snippet": "<a href=\"https://news.google.com/rss/articles/CBMi7AFBVV95cUxNZ1Q0c3phWFA1b1pQbllTLU5USkNtaUE4Ukt4cnRsT0w3V043a1FjcVd2T25NVWNkOFBSQVhJTXhCRVVvcTlmZWJZdHU1UkxIcGpGallDQWVCb2o5dVlwdzExbFo2aVE2UTd1SGtpS1",
      "impact": "down"
    },
    {
      "title": "Silver Futures Decline to Rs 2.23 Lakh/kg on MCX",
      "url": "https://news.google.com/rss/articles/CBMiogFBVV95cUxPaFZQRkQ4YWRpRVEwUDNoNlhINnlaRGwxblYzRTRtVmJ1cVk3Ml9GWml0UFhyUzJvdXA4Sms5by0xUVBseXBaQ3dxZkpFcGZBUW1SUXNlU3Y3dTM3OGhpNW5FMGJuQ0ZzZEFYaUkySTBIM2NFS2paUVlSNnRwU1VlT1lrSGZFUVpIcElONEt6LVBBUVFYODkzenp5dElsRmdNdlHSAacBQVVfeXFMTXUyTXJkelBoa0V0VE1ZOTJkQmxsVjJDcjVVTUM0eWR0UjlodVdCeEgwdEhxTE9rdW5XMWkydldyb1FndXIzWkMyQlNvVGVhWF9qNExnbjBDemhuYjhPRU9tcE94QlAwMU50aXBiVFkwQXgxSVR2RVNhc0RNWFcwWHd6eWZsT3k3eDFPNzU4aFl4RmVqMzJnZzlpZURXeHBFdGFQd3FoZWc?oc=5",
      "source": "Rediff MoneyWiz",
      "publishedAt": "2026-07-01T09:25:46.000Z",
      "snippet": "<a href=\"https://news.google.com/rss/articles/CBMiogFBVV95cUxPaFZQRkQ4YWRpRVEwUDNoNlhINnlaRGwxblYzRTRtVmJ1cVk3Ml9GWml0UFhyUzJvdXA4Sms5by0xUVBseXBaQ3dxZkpFcGZBUW1SUXNlU3Y3dTM3OGhpNW5FMGJuQ0ZzZEFYaUkyST",
      "impact": "twoway"
    },
    {
      "title": "Silver Price Forecast: $55.60 Year-to-Date Low Exposed as Ascending Trendline Rejections Fuel Bearish Continuation",
      "url": "https://news.google.com/rss/articles/CBMi6wFBVV95cUxPV051cm1kbV9NOXlLLV92c3pZRENUa2VsZURHMmZRSmZYOENJakpzXzFEQ3RFVHNmbjhWZEM3dkRWNEkzenlEWG5DRWZab3ZrUVFxbEZLbDdpLWJhN3c1XzdwbXdvVk8xeDROY0stb09XMExzenZUMzlSQXRiem9GZkxiczR4VUx5R3NsQjZTZEJBZ21MNEQ4a3JOUFg4Rm1qTFpXVEhFWEJFX0pyV3gtZXdWZkVFMGtzdTdzRzBZWVA2TXZmcHJZaGV5bTBYU0EtMHEwNUtPX3R2Qlh5Wm5jNHo4R2l5SUp3SzFj?oc=5",
      "source": "FXLeaders",
      "publishedAt": "2026-07-01T07:01:43.000Z",
      "snippet": "<a href=\"https://news.google.com/rss/articles/CBMi6wFBVV95cUxPV051cm1kbV9NOXlLLV92c3pZRENUa2VsZURHMmZRSmZYOENJakpzXzFEQ3RFVHNmbjhWZEM3dkRWNEkzenlEWG5DRWZab3ZrUVFxbEZLbDdpLWJhN3c1XzdwbXdvVk8xeDROY0stb0",
      "impact": "down"
    },
    {
      "title": "Gold and Silver Price Forecast: Gold Falls Below $4,000 as Fed Bets Rise",
      "url": "https://news.google.com/rss/articles/CBMivAFBVV95cUxPS29wYl92MmhrME9WLTYxMTJYVVd4WXVrZzNnNU1QMENoSmR4dGNMazdVQW9xdVotTE9CSU1XSkFlNklSRFU0OWU4ZTNsSmlfOUpGU25xWmZHOU00LUFZSWhkci02OFNUZUVKSmxpTzJQZzZwZFEtc2lqdGdycFBWam91X2pOS2NQUV9NUkhjQkZydE9yLWtTRnNBaEYzbFUxbU1JOFJGLWc5U3BVMS1IMWJFQ2o1LTltbGd0Sg?oc=5",
      "source": "FXEmpire",
      "publishedAt": "2026-07-01T04:06:00.000Z",
      "snippet": "<a href=\"https://news.google.com/rss/articles/CBMivAFBVV95cUxPS29wYl92MmhrME9WLTYxMTJYVVd4WXVrZzNnNU1QMENoSmR4dGNMazdVQW9xdVotTE9CSU1XSkFlNklSRFU0OWU4ZTNsSmlfOUpGU25xWmZHOU00LUFZSWhkci02OFNUZUVKSmxpTz",
      "impact": "down"
    },
    {
      "title": "Gold, Silver Price Today: Check Rates In Mumbai, Delhi, Chennai, Kolkata, Bangalore",
      "url": "https://news.google.com/rss/articles/CBMixwFBVV95cUxOUmh4bzhnRWpCOF93aXRCV1ZGU25oVXNyUExWdUlpeGhuUm5IbEJ0dUI3N3FhRTUta2YxR0RKQ3BSSDFyTkFhN3k4YzZJZWowZ29nUHg0bmEwQmxPeFViX3NzcDkwQk4xMHlCaGJ5bmZKRnk4N1l2bkJnNlgxT0xrSG5lcHpKQ2gydXJHTkRzRFFELWcyQUZ3cFhwUUFlYy1VNDBTb0dhUFJqWTRzN0FmMkJmQWNsYTdpZzU4UklORW9acnE2YWFz0gHPAUFVX3lxTE9jalI0WjJNMW9FT2NpenVRNk5sS1o3Qi1BV0twczlUYXdzMkZBTXltX25zeHRRaWVNQ0pFelBVQ2JjOWd5STBtU0tMMm5PZUpWaVF1cUhzd1plaXRQZEw4MV81RU5jdVFZc29OMnFsTUhFQi05NEZ2LVpCYmVacXhrNVVIVkE0dExHbDZhUy1UMTQ2UTR6d0dpX1c4RkttaTVuQXU3TWpmSjdWclhqbHpWWjVpQkJ5LWNQbmJSWVh0U1ZVOENPMTZGQ2NxMG5XMA?oc=5",
      "source": "NDTV Profit",
      "publishedAt": "2026-07-01T03:31:26.000Z",
      "snippet": "<a href=\"https://news.google.com/rss/articles/CBMixwFBVV95cUxOUmh4bzhnRWpCOF93aXRCV1ZGU25oVXNyUExWdUlpeGhuUm5IbEJ0dUI3N3FhRTUta2YxR0RKQ3BSSDFyTkFhN3k4YzZJZWowZ29nUHg0bmEwQmxPeFViX3NzcDkwQk4xMHlCaGJ5bm",
      "impact": "twoway"
    },
    {
      "title": "Silver Panic: Hidden Chinese Stockpiles Trigger Unprecedented Rally",
      "url": "https://news.google.com/rss/articles/CBMirgFBVV95cUxNRllyX0FRRkRSVDhmekh2RzNkaXBrbGRGcWo1eFRmNkJzOVZLbVdOcHYyYVZZLWlxS2tfOXljTXZYd3lKbWRkczVMamlQNUR6c0tMVXhoR0ZGT3h3SGxfQkQ4cDZ4WWoyOWZmSnIwbGhXTElrN0FQTmczVHcyb2JvY0tQQ0FEeWwwWEJPT050eXdMVkVYYjhSLTFUcmJfVzFMdVlndVdTRHFyMXI0LUE?oc=5",
      "source": "FXLeaders",
      "publishedAt": "2026-07-01T02:07:44.000Z",
      "snippet": "<a href=\"https://news.google.com/rss/articles/CBMirgFBVV95cUxNRllyX0FRRkRSVDhmekh2RzNkaXBrbGRGcWo1eFRmNkJzOVZLbVdOcHYyYVZZLWlxS2tfOXljTXZYd3lKbWRkczVMamlQNUR6c0tMVXhoR0ZGT3h3SGxfQkQ4cDZ4WWoyOWZmSnIwbG",
      "impact": "up"
    },
    {
      "title": "Current price of silver as of Tuesday, June 30, 2026",
      "url": "https://news.google.com/rss/articles/CBMib0FVX3lxTE9aSEpyTFdTNTVILVU5X2MyWFQ4bEdMcGpnX0NEU3g2aFdrOFVwRndRMUMteHp1YU1zRDAwUm92emlRNkpUaDQxRkVFQlVXWmxXb2l4SVBUT25CUmxqRzhBdVNTWDVRNTF4UUQ5NUhFOA?oc=5",
      "source": "Fortune",
      "publishedAt": "2026-06-30T13:00:00.000Z",
      "snippet": "<a href=\"https://news.google.com/rss/articles/CBMib0FVX3lxTE9aSEpyTFdTNTVILVU5X2MyWFQ4bEdMcGpnX0NEU3g2aFdrOFVwRndRMUMteHp1YU1zRDAwUm92emlRNkpUaDQxRkVFQlVXWmxXb2l4SVBUT25CUmxqRzhBdVNTWDVRNTF4UUQ5NUhFOA",
      "impact": "twoway"
    },
    {
      "title": "Silver Price Forecast 2026–2030: Outlook, INR Rates & Key Drivers",
      "url": "https://news.google.com/rss/articles/CBMickFVX3lxTE9VREVUUTg0eGd6a2RlaWJtYWx1WVl1azM5a3lSbG5fVXk1aU9rQV9heGtXMVhUbm9ONUhEZU9XdHU0c25jaF9ocUFpTzNjZ0w4ZFM3OTFkVVU4R3pNMEtHQVc3WmV5RXpCTDBsSzJQYUJ0QQ?oc=5",
      "source": "CoinDCX",
      "publishedAt": "2026-06-30T12:00:00.000Z",
      "snippet": "<a href=\"https://news.google.com/rss/articles/CBMickFVX3lxTE9VREVUUTg0eGd6a2RlaWJtYWx1WVl1azM5a3lSbG5fVXk1aU9rQV9heGtXMVhUbm9ONUhEZU9XdHU0c25jaF9ocUFpTzNjZ0w4ZFM3OTFkVVU4R3pNMEtHQVc3WmV5RXpCTDBsSzJQYU",
      "impact": "twoway"
    },
    {
      "title": "Silver Plummets Under Pressure From Stronger Dollar. Forecast as of 30.06.2026",
      "url": "https://news.google.com/rss/articles/CBMi-gFBVV95cUxNNWxkT2pvUWlUTHYxczFNcHVSUF85d1RSVjVDbHdPa0ZpNWVRYnVnU0hNUDdxb25Ra3ZkZ3dPYmZaNndQZFpMaWJfV2VycUVoQnFWTmo2cVlLNEsyTEstdDB2bmphM3VUNlp0UzdiRE1nN0laMnpJZjR4T2tBM2doMDNYLXBYOU1pVnFxNE51V0ZPNFJuemdUVXg1UVVQOFI4TjBKTEpDaUxVbFFsRXJzeVJWclVYaUFPVWNCdXdxYzRIZGV4Szh2ZmtDQUgyOUJNUUlJaDVrcUpKZUVxRGhQUzM3SnY4eGEzS1dBZ0RfdUVoUHJlUV9PV3VB?oc=5",
      "source": "LiteFinance",
      "publishedAt": "2026-06-30T11:25:22.000Z",
      "snippet": "<a href=\"https://news.google.com/rss/articles/CBMi-gFBVV95cUxNNWxkT2pvUWlUTHYxczFNcHVSUF85d1RSVjVDbHdPa0ZpNWVRYnVnU0hNUDdxb25Ra3ZkZ3dPYmZaNndQZFpMaWJfV2VycUVoQnFWTmo2cVlLNEsyTEstdDB2bmphM3VUNlp0UzdiRE",
      "impact": "down"
    },
    {
      "title": "Gold declines Rs 800; Silver rebounds Rs 6,000 in Delhi",
      "url": "https://news.google.com/rss/articles/CBMiqgFBVV95cUxPSUJQd3A4TlYyUWJlbVZvTGV0eFI3VVlXVFVsaENmWk9PMWtsNzNmS1dQREZubDB5dnFyMmhuSzViOS1iMkUtOU9PVmMtQXhDQWcyU1JsUldmcFlqaGlqWXZUR19BRjRmajc0aFJSQ1d5N0F0NnRkRzFsbTh0ZVlwSWZKekdNdFBOdG9HcTY4d21Pa0JYVkNDNHl5bnhBRkRHbW84bG1YMk5aZ9IBrwFBVV95cUxQMEI4LXpkRmktZFhzUzc4R2tsTnI1TGU4bDJ4N2lYV0h4NU40NUJlQVEzMjBwWUFYWmNIekp2MnZqVWh4V2wtNUdnY3dRUW41bnRPMGR2dG1rUmF1RE5HWjVjVk1FaWtoYUMtUzJINUowSG5SdzU1eTdBN3EwRTZ0dktQRmtxclJzaENKSG5jRzc1a1B6TF8zMGpuZ01nbTJaMi1YYzgxbFJOWnh3NnFB?oc=5",
      "source": "Rediff MoneyWiz",
      "publishedAt": "2026-06-30T11:21:24.000Z",
      "snippet": "<a href=\"https://news.google.com/rss/articles/CBMiqgFBVV95cUxPSUJQd3A4TlYyUWJlbVZvTGV0eFI3VVlXVFVsaENmWk9PMWtsNzNmS1dQREZubDB5dnFyMmhuSzViOS1iMkUtOU9PVmMtQXhDQWcyU1JsUldmcFlqaGlqWXZUR19BRjRmajc0aFJSQ1",
      "impact": "down"
    },
    {
      "title": "Silver squeezed at $61 resistance zone: Live levels By Investing.com",
      "url": "https://news.google.com/rss/articles/CBMitAFBVV95cUxPZ3hDQmVONTZjMXBHb0d1X0NwdWpVanYxckpYMm5EdE1paW43d3ptTmdVdFJtSXdidW83b2M0eVhZX0JIdS1Dem9CRHVrSWtHUk1VNVRSUTlJZ3g4ZW9jc2ZBOFQxYjdac1c3UjBRRjhWNTBHc3ZrWWt3NTRmN1BtbHdaeVJPSXExU1VlM3g5UFdXS0pGUEc4RnVqWDZCWjhpaXR6N2VoR0UzRkloQkZRMU94bjY?oc=5",
      "source": "Investing.com Canada",
      "publishedAt": "2026-06-30T07:46:01.000Z",
      "snippet": "<a href=\"https://news.google.com/rss/articles/CBMitAFBVV95cUxPZ3hDQmVONTZjMXBHb0d1X0NwdWpVanYxckpYMm5EdE1paW43d3ptTmdVdFJtSXdidW83b2M0eVhZX0JIdS1Dem9CRHVrSWtHUk1VNVRSUTlJZ3g4ZW9jc2ZBOFQxYjdac1c3UjBRRj",
      "impact": "up"
    },
    {
      "title": "Silver Price Forecasts: XAG/USD picks up, nearing $60.00 with the bearish trend intact",
      "url": "https://news.google.com/rss/articles/CBMiwwFBVV95cUxNSXY5X2ozVDJCVW9QdGJNXzFRaS1pbk80ZlpZWGEwWmNXVXg0NDdHaDBvMHJiNFhDQ1dHbWM3RjVPd2VpSmNpaXFGbV9jeFVPc1hYc3g0M2VPOHktNFRmT1F2TDkxbWpqWGRobUZlVzIzamNEdUxiOHZabW5VVGpnYk5RT040VVhSTmlnejJ5eTMycGhVb3BLb1ZmUzhDWk56RVRxSmFibzNCY3d6ZDdWWHBtWFpUemhfb1hVUVpLcDlMZDQ?oc=5",
      "source": "FXStreet",
      "publishedAt": "2026-06-30T07:02:18.000Z",
      "snippet": "<a href=\"https://news.google.com/rss/articles/CBMiwwFBVV95cUxNSXY5X2ozVDJCVW9QdGJNXzFRaS1pbk80ZlpZWGEwWmNXVXg0NDdHaDBvMHJiNFhDQ1dHbWM3RjVPd2VpSmNpaXFGbV9jeFVPc1hYc3g0M2VPOHktNFRmT1F2TDkxbWpqWGRobUZlVz",
      "impact": "down"
    }
  ],
  "events": [
    {
      "name": "US Jobs (NFP)",
      "date": "2026-07-02",
      "kind": "us_jobs",
      "impact": "twoway",
      "weight": 2,
      "effect": "Hot payrolls → hawkish Fed, ↑ yields & USD → silver DOWN. Weak jobs → silver UP."
    },
    {
      "name": "US CPI",
      "date": "2026-07-10",
      "kind": "us_cpi",
      "impact": "twoway",
      "weight": 3,
      "effect": "Hot CPI → rate-cut hopes fade, real yields up → silver DOWN (inflation-hedge bid partly offsets)."
    },
    {
      "name": "Fed FOMC",
      "date": "2026-07-29",
      "kind": "fomc",
      "impact": "twoway",
      "weight": 3,
      "effect": "Dovish / cut → silver UP. Hawkish hold or hike risk → silver DOWN. Biggest IV-crush event."
    }
  ]
}
